{
  "deposited_date" : "07/02/2008"
  "legislature" : CommonsLords
  "notes" : "Items I, II & III in hard copy only."
  "link_to_paper" : "http://www.parliament.uk/deposits/depositedpapers/2008/DEP2008-0398.zip"
  "year" : "2008"
  "description" : "I. North east of England regional spatial strategy: the government's further proposed changes to the draft revision submitted by the North East Assembly. 254 p. II. Statement of reasons. [CD-ROM] III. North East RSS sustainability appraisal: assessment of further proposed changes and final conclusions. 43 p. IV. Accompanying documents and addenda."
  "department" : "Government Office for the North East Dept for Communities and Local Government Environ UK"
}