{
  "deposited_date" : "02/12/2009",
  "legislature" : ["Commons"],
  "link_to_paper" : "http://www.parliament.uk/deposits/depositedpapers/2009/DEP2009-3122.tif",
  "year" : "2009",
  "description" : "Letter dated 09/12/2009 from John McCaughan (Superintendent, PSNI) to Jeffrey Donaldson MP regarding police officers assigned to uniformed response duties in each district command unit also assigned following assignment to administrative duties observing normal office hours. 2 p.",
  "department" : "Northern Ireland Office"
}