{
  "deposited_date" : "28/11/2007",
  "legislature" : ["Commons"],
  "link_to_paper" : "http://www.parliament.uk/deposits/depositedpapers/2007/DEP2007-0178.pdf",
  "year" : "2007",
  "description" : "Analysis of difficulties in setting up pilot projects to reduce or eliminate discards in cooperation with the fishing industry in Member States of the European Union: interim report. FISH2006/15 - Lot 1. 30 p.",
  "department" : "Centre for Environment Fisheries and Aquaculture Science Dept for Environment Food and Rural Affairs"
}